ga/GA360.py
ga/auth/AzureAuthProvider.py
ga/auth/GoogleAuthProvider.py
ga/auth/__init__.py
ga/exceptions/InvalidConfigurationException.py
ga/exceptions/NotAuthorizedException.py
ga/exceptions/NotFound.py
ga/exceptions/__init__.py
ga/model/Dataset.py
ga/model/__init__.py
ga/persist/AzurePersistingHandler.py
ga/persist/FilePersistingHandler.py
ga/persist/FilePersistingMultiHandler.py
ga/persist/__init__.py
ga/utils/__init__.py
ga/utils/list_utils.py
odap_ga_downloader-1.0.5.dist-info/LICENSE
odap_ga_downloader-1.0.5.dist-info/WHEEL
odap_ga_downloader-1.0.5.dist-info/METADATA
odap_ga_downloader-1.0.5.dist-info/RECORD
