Metadata-Version: 2.1
Name: odap-ga-downloader
Version: 1.0.5
Summary: Extractor for Google analytics
Home-page: https://github.com/DataSentics/odap-ga-downloader
License: MIT
Author: Roman Novosad
Author-email: roman.novosad@datasentics.com
Requires-Python: >=3.7.2,<3.10.0
Classifier: License :: OSI Approved :: MIT License
Classifier: Operating System :: OS Independent
Classifier: Programming Language :: Python :: 3
Classifier: Programming Language :: Python :: 3.8
Classifier: Programming Language :: Python :: 3.9
Requires-Dist: azure-identity (>=1.7.0,<2.0.0)
Requires-Dist: azure-storage-blob (>=12.9.0,<13.0.0)
Requires-Dist: google-auth (>=1.30.0,<2.0.0)
Requires-Dist: google-cloud (>=0.34.0,<0.35.0)
Requires-Dist: google-cloud-bigquery (>=2.26.0,<3.0.0)
Requires-Dist: google-cloud-storage (>=1.42.2,<2.0.0)
Requires-Dist: requests (>=2.25.1,<3.0.0)
Requires-Dist: wrapt (>=1.12.1,<2.0.0)
Project-URL: Repository, https://github.com/DataSentics/odap-ga-downloader
